src/__init__.py
src/operations.py
calculat0r_lolxdd-0.1.0.dist-info/METADATA
calculat0r_lolxdd-0.1.0.dist-info/WHEEL
calculat0r_lolxdd-0.1.0.dist-info/top_level.txt
calculat0r_lolxdd-0.1.0.dist-info/RECORD
